MANIFEST.in
README.md
linuxadmin.service
setup.cfg
setup.py
src/linuxadmin.egg-info/PKG-INFO
src/linuxadmin.egg-info/SOURCES.txt
src/linuxadmin.egg-info/dependency_links.txt
src/linuxadmin.egg-info/entry_points.txt
src/linuxadmin.egg-info/requires.txt
src/linuxadmin.egg-info/top_level.txt
src/thinclient/__init__.py
src/thinclient/auto_update.py
src/thinclient/metrics.py
src/thinclient/register.py
src/thinclient/setup.py
src/thinclient/thinclient.py
src/thinclient/pytransform/__init__.py
src/thinclient/pytransform/_pytransform.so
tests/testTqdm.py