Metadata-Version: 2.1
Name: linuxadmin
Version: 0.0.1
Summary: Linux Admin ThinClient for Linux
Author: MustansirG
Author-email: me@mustansirg.in
Classifier: Programming Language :: Python :: 3
Classifier: Programming Language :: Python :: 3 :: Only
Classifier: Programming Language :: Python :: 3.9
